{"player":{"x":4.239943666337605,"y":12.768166089965398,"sx":1.8,"sy":2.7},"door":null,"obstacles":[{"x":2,"y":14,"sx":13,"sy":3,"type":0},{"x":15,"y":2,"sx":4,"sy":15,"type":0},{"x":19,"y":-1,"sx":4,"sy":3,"type":0},{"x":23,"y":-4,"sx":3,"sy":3,"type":0},{"x":26,"y":-7,"sx":3,"sy":3,"type":0}],"unstatics":[],"targets":[{"x":15,"y":2,"sx":2,"sy":5}],"triggers":[],"loadTriggers":[],"obstacleTiles":[{"nr":0,"x":15,"y":107},{"nr":0,"x":16,"y":107},{"nr":0,"x":17,"y":107},{"nr":0,"x":18,"y":107},{"nr":0,"x":18,"y":106},{"nr":0,"x":18,"y":105},{"nr":0,"x":18,"y":104},{"nr":0,"x":18,"y":103},{"nr":0,"x":18,"y":102},{"nr":0,"x":17,"y":102},{"nr":0,"x":17,"y":103},{"nr":0,"x":17,"y":104},{"nr":0,"x":17,"y":105},{"nr":0,"x":17,"y":106},{"nr":0,"x":17,"y":108},{"nr":0,"x":17,"y":109},{"nr":0,"x":17,"y":110},{"nr":0,"x":17,"y":111},{"nr":0,"x":17,"y":112},{"nr":0,"x":17,"y":113},{"nr":0,"x":16,"y":113},{"nr":0,"x":16,"y":114},{"nr":0,"x":16,"y":115},{"nr":0,"x":17,"y":115},{"nr":0,"x":18,"y":115},{"nr":0,"x":18,"y":116},{"nr":0,"x":18,"y":114},{"nr":0,"x":18,"y":113},{"nr":0,"x":18,"y":112},{"nr":0,"x":18,"y":111},{"nr":0,"x":18,"y":110},{"nr":0,"x":18,"y":109},{"nr":0,"x":18,"y":108},{"nr":0,"x":16,"y":108},{"nr":0,"x":15,"y":108},{"nr":0,"x":15,"y":109},{"nr":0,"x":15,"y":110},{"nr":0,"x":15,"y":111},{"nr":0,"x":15,"y":112},{"nr":0,"x":15,"y":113},{"nr":0,"x":15,"y":114},{"nr":0,"x":17,"y":116},{"nr":0,"x":16,"y":116},{"nr":0,"x":15,"y":116},{"nr":0,"x":14,"y":116},{"nr":0,"x":13,"y":116},{"nr":0,"x":12,"y":116},{"nr":0,"x":11,"y":116},{"nr":0,"x":10,"y":116},{"nr":0,"x":9,"y":116},{"nr":0,"x":9,"y":115},{"nr":0,"x":8,"y":115},{"nr":0,"x":7,"y":115},{"nr":0,"x":6,"y":115},{"nr":0,"x":5,"y":115},{"nr":0,"x":4,"y":115},{"nr":0,"x":3,"y":115},{"nr":0,"x":3,"y":114},{"nr":0,"x":2,"y":114},{"nr":0,"x":4,"y":114},{"nr":0,"x":5,"y":114},{"nr":0,"x":6,"y":114},{"nr":0,"x":7,"y":114},{"nr":0,"x":8,"y":114},{"nr":0,"x":9,"y":114},{"nr":0,"x":10,"y":114},{"nr":0,"x":11,"y":114},{"nr":0,"x":12,"y":114},{"nr":0,"x":13,"y":114},{"nr":0,"x":14,"y":114},{"nr":0,"x":15,"y":115},{"nr":0,"x":14,"y":115},{"nr":0,"x":13,"y":115},{"nr":0,"x":12,"y":115},{"nr":0,"x":11,"y":115},{"nr":0,"x":10,"y":115},{"nr":0,"x":2,"y":115},{"nr":0,"x":2,"y":116},{"nr":0,"x":3,"y":116},{"nr":0,"x":4,"y":116},{"nr":0,"x":5,"y":116},{"nr":0,"x":6,"y":116},{"nr":0,"x":7,"y":116},{"nr":0,"x":8,"y":116},{"nr":0,"x":17,"y":114},{"nr":0,"x":16,"y":112},{"nr":0,"x":16,"y":111},{"nr":0,"x":16,"y":110},{"nr":0,"x":16,"y":109},{"nr":0,"x":22,"y":101},{"nr":0,"x":21,"y":101},{"nr":0,"x":20,"y":101},{"nr":0,"x":19,"y":101},{"nr":0,"x":19,"y":100},{"nr":0,"x":19,"y":99},{"nr":0,"x":20,"y":99},{"nr":0,"x":21,"y":99},{"nr":0,"x":21,"y":100},{"nr":0,"x":22,"y":99},{"nr":0,"x":22,"y":100},{"nr":0,"x":20,"y":100},{"nr":0,"x":23,"y":96},{"nr":0,"x":24,"y":96},{"nr":0,"x":25,"y":96},{"nr":0,"x":25,"y":97},{"nr":0,"x":24,"y":97},{"nr":0,"x":23,"y":97},{"nr":0,"x":23,"y":98},{"nr":0,"x":24,"y":98},{"nr":0,"x":25,"y":98},{"nr":0,"x":27,"y":94},{"nr":0,"x":28,"y":94},{"nr":0,"x":28,"y":93},{"nr":0,"x":27,"y":93},{"nr":0,"x":26,"y":94},{"nr":0,"x":26,"y":93},{"nr":0,"x":26,"y":95},{"nr":0,"x":27,"y":95},{"nr":0,"x":28,"y":95}],"targetTiles":[{"nr":0,"x":15,"y":102},{"nr":0,"x":16,"y":102},{"nr":0,"x":16,"y":103},{"nr":0,"x":15,"y":103},{"nr":0,"x":15,"y":104},{"nr":0,"x":16,"y":104},{"nr":0,"x":16,"y":105},{"nr":0,"x":15,"y":105},{"nr":0,"x":15,"y":106},{"nr":0,"x":16,"y":106}],"lavaTiles":[],"soundtrack":"Try and Solve This Loop.wav"}